{
  "files": {
    "soma_impares.py": {
      "category": "answer",
      "data": "# coding: utf-8\n# Aluno: Walisson Nascimento de Farias\n# Matr\u00edcula: 117210716\n# UFCG - Per\u00edodo: 2017.2\n# Unidade 4\n# QUEST\u00c3O: Soma \u00daltimos \u00cdmpares\n\nquantidade = int(raw_input())\nlimite = int(raw_input())\nlista = []\n\nfor c in range(quantidade):\n\tnumero = int(raw_input())\n\tif numero % 2 != 0:\n\t\tlista.append(numero)\n\nsoma = 0\nfor i in range(-1, -len(lista) -1, -1):\n\tif lista[i] + soma < limite:\n\t\tsoma += lista[i]\n\telse:\n\t\tbreak\n\nprint soma\n",
      "name": "soma_impares.py"
    },
    "qcheck.json": {
      "category": "public",
      "data": "{\n  \"quality\": [\n    {\n      \"cc\": 5,\n      \"pep8\": 0,\n      \"lloc\": 14,\n      \"vhalstead\": 70.32,\n      \"header\": 4\n    }\n  ]\n}"
    }
  },
  "kind": "assignment",
  "name": null,
  "checksum": "9988f714621b7ec0861065763612b1be",
  "iid": 5265606962053120,
  "activity_revision": "1.0.1"
}